openai_forward/__init__.py
openai_forward/__main__.py
openai_forward/app.py
openai_forward/console.py
openai_forward/custom_slowapi.py
openai_forward/decorators.py
openai_forward/helper.py
openai_forward/settings.py
openai_forward/cache/__init__.py
openai_forward/cache/database.py
openai_forward/cache/chat/__init__.py
openai_forward/cache/chat/chat_completions.py
openai_forward/cache/chat/response.py
openai_forward/cache/chat/tokenizer.py
openai_forward/cache/embedding/__init__.py
openai_forward/cache/embedding/response.py
openai_forward/config/__init__.py
openai_forward/config/interface.py
openai_forward/content/__init__.py
openai_forward/content/config.py
openai_forward/content/helper.py
openai_forward/content/openai.py
openai_forward/forward/__init__.py
openai_forward/forward/core.py
openai_forward/webui/__init__.py
openai_forward/webui/chat.py
openai_forward/webui/helper.py
openai_forward/webui/run.py
openai_forward-0.8.1.dist-info/METADATA
openai_forward-0.8.1.dist-info/WHEEL
openai_forward-0.8.1.dist-info/entry_points.txt
openai_forward-0.8.1.dist-info/licenses/LICENSE
openai_forward-0.8.1.dist-info/RECORD
