Metadata-Version: 2.3
Name: openai_forward
Version: 0.8.1
Summary: 🚀 OpenAI-Forward 是一个专为大型语言模型设计的高级转发代理，提供包括用户请求速率控制、Token速率限制和自定义API密钥等增强功能。该服务可用于代理本地模型和云端模型。OpenAI API Reverse Proxy
Project-URL: Homepage, https://github.com/KenyonY/openai-forward
Project-URL: Documentation, https://github.com/KenyonY/openai-forward#openai-forward
Project-URL: Issues, https://github.com/KenyonY/openai-forward/issues
Project-URL: Source, https://github.com/KenyonY/openai-forward
Author-email: kunyuan <beidongjiedeguang@gmail.com>
License-Expression: MIT
License-File: LICENSE
Keywords: OpenAI API Forwarding,chatgpt,fastapi,openai,openai-api,openai-proxy,python,streaming-api
Classifier: Development Status :: 5 - Production/Stable
Classifier: Operating System :: OS Independent
Classifier: Programming Language :: Python :: 3
Requires-Python: >=3.8
Requires-Dist: aiohttp>=3.8.5
Requires-Dist: fastapi>=0.90.0
Requires-Dist: fire
Requires-Dist: flaxkv[client]>=0.2.7
Requires-Dist: httpx[http2]>=0.26.0
Requires-Dist: loguru>=0.7.0
Requires-Dist: msgpack
Requires-Dist: orjson>=3.9
Requires-Dist: python-dotenv
Requires-Dist: pytz
Requires-Dist: pyzmq
Requires-Dist: rich
Requires-Dist: slowapi==0.1.9
Requires-Dist: tiktoken>=0.5.1
Requires-Dist: tomli
Requires-Dist: tomli-w
Requires-Dist: uvicorn>=0.21.0
Provides-Extra: benchmark
Requires-Dist: openai>=1.3.0; extra == 'benchmark'
Provides-Extra: dev
Requires-Dist: openai>=1.3.0; extra == 'dev'
Requires-Dist: schedule; extra == 'dev'
Requires-Dist: sparrow-python; extra == 'dev'
Provides-Extra: test
Requires-Dist: openai>=1.3.0; extra == 'test'
Requires-Dist: psutil; extra == 'test'
Requires-Dist: pytest; extra == 'test'
Requires-Dist: pytest-aiohttp; extra == 'test'
Requires-Dist: trio; extra == 'test'
Requires-Dist: twisted; extra == 'test'
Provides-Extra: webui
Requires-Dist: streamlit~=1.30.0; extra == 'webui'
